{
  "name": "Cauldron",
  "nativeApps": [
    {
      "name": "Shopping",
      "platforms": [
        {
          "name": "android",
          "versions": [
            {
              "name": "0.0.1",
              "codePush": {},
              "container": {
                "jsApiImpls": [],
                "miniApps": [
                  "@tranducduong1994/shopping-list-miniapp@0.0.1"
                ],
                "nativeDeps": [
                  "ernnavigation-api-impl-native@1.6.10",
                  "ernnavigation-api@1.3.0",
                  "react-native-electrode-bridge@1.5.27",
                  "react-native@0.64.0"
                ],
                "ernVersion": "0.48.4"
              },
              "isReleased": false,
              "nativeDeps": [],
              "yarnLocks": {
                "container": "0776b2f0-68c0-48a9-bda4-6f0b8734b784"
              },
              "containerVersion": "1.0.0"
            }
          ]
        },
        {
          "name": "ios",
          "versions": [
            {
              "name": "0.0.1",
              "codePush": {},
              "container": {
                "jsApiImpls": [],
                "miniApps": [
                  "@tranducduong1994/shopping-list-miniapp@0.0.2",
                  "@tranducduong1994/shopping-product-miniapp@0.0.2"
                ],
                "nativeDeps": [
                  "ernnavigation-api-impl-native@1.6.10",
                  "ernnavigation-api@1.3.0",
                  "react-native-electrode-bridge@1.5.27",
                  "react-native@0.64.0"
                ],
                "ernVersion": "0.48.4"
              },
              "isReleased": false,
              "nativeDeps": [],
              "yarnLocks": {
                "container": "103304da-fba8-41d0-a746-d3f0d6c682fc"
              },
              "containerVersion": "1.0.0"
            }
          ]
        }
      ]
    }
  ],
  "schemaVersion": "3.0.0"
}
